angle_emb/__init__.py
angle_emb/angle.py
angle_emb/angle_trainer.py
angle_emb/base.py
angle_emb/evaluation.py
angle_emb/loss.py
angle_emb/utils.py
angle_emb/version.py
angle_emb-0.6.0.dist-info/licenses/LICENSE
docs/conf.py
scripts/convert_to_sentence_transformer.py
scripts/push_bert_model.py
scripts/push_llm_model.py
angle_emb-0.6.0.dist-info/METADATA
angle_emb-0.6.0.dist-info/WHEEL
angle_emb-0.6.0.dist-info/entry_points.txt
angle_emb-0.6.0.dist-info/top_level.txt
angle_emb-0.6.0.dist-info/RECORD
