Metadata-Version: 2.4
Name: angle_emb
Version: 0.6.0
Summary: AnglE-optimize Text Embeddings
Author-email: sean lee <xmlee97@gmail.com>
Keywords: angle_emb
Classifier: Development Status :: 5 - Production/Stable
Classifier: Intended Audience :: Developers
Classifier: License :: OSI Approved :: BSD License
Classifier: Natural Language :: English
Classifier: Programming Language :: Python :: 3.10
Classifier: Programming Language :: Python :: 3.11
Classifier: Programming Language :: Python :: 3.12
Requires-Python: >=3.10
License-File: LICENSE
Requires-Dist: bitsandbytes>=0.48.1
Requires-Dist: boltons>=25.0.0
Requires-Dist: datasets>=4.2.0
Requires-Dist: einops>=0.8.1
Requires-Dist: peft>=0.17.1
Requires-Dist: prettytable>=3.16.0
Requires-Dist: scikit-learn>=1.7.2
Requires-Dist: scipy>=1.15.3
Requires-Dist: transformers>=4.57.0
Provides-Extra: dev
Requires-Dist: pytest; extra == "dev"
Requires-Dist: pytest-cov; extra == "dev"
Requires-Dist: pytest-sugar; extra == "dev"
Provides-Extra: wandb
Requires-Dist: wandb; extra == "wandb"
Dynamic: license-file
